bdmodels/__init__.py
bdmodels/apps.py
bdmodels/fields.py
bdmodels/migration_ops.py
bdmodels/models.py
broken_down_models-0.5.0.dist-info/LICENSE
broken_down_models-0.5.0.dist-info/METADATA
broken_down_models-0.5.0.dist-info/WHEEL
broken_down_models-0.5.0.dist-info/RECORD
