Metadata-Version: 2.1
Name: broken-down-models
Version: 0.5.0
Summary: A set of utlities for breaking a large Django model down to separate components
Home-page: https://github.com/Matific/broken-down-models
License: MIT
Keywords: Django,models,database,optimization,refactoring
Author: Shai Berger
Author-email: shai.berger@slatescience.com
Requires-Python: >=3.9,<4.0
Classifier: Development Status :: 4 - Beta
Classifier: Framework :: Django
Classifier: Framework :: Django :: 4.2
Classifier: Framework :: Django :: 5.0
Classifier: Framework :: Django :: 5.1
Classifier: Framework :: Django :: 5.2
Classifier: Intended Audience :: Developers
Classifier: License :: OSI Approved :: MIT License
Classifier: Programming Language :: Python :: 3
Classifier: Programming Language :: Python :: 3.9
Classifier: Programming Language :: Python :: 3.10
Classifier: Programming Language :: Python :: 3.11
Classifier: Topic :: Database
Requires-Dist: django (>=4.2)
Project-URL: Documentation, https://broken-down-models.readthedocs.io/en/latest/intro.html
